adsorption/__init__.py
adsorption/_core/__init__.py
adsorption/_core/abc.py
adsorption/_core/calculator.py
adsorption/_core/interface.py
adsorption/attempt/__init__.py
adsorption/attempt/monatom.py
adsorption/optmization/__init__.py
adsorption-0.0.3.dist-info/licenses/LICENSE
adsorption-0.0.3.dist-info/METADATA
adsorption-0.0.3.dist-info/WHEEL
adsorption-0.0.3.dist-info/top_level.txt
adsorption-0.0.3.dist-info/RECORD
