Metadata-Version: 2.4
Name: adsorption
Version: 0.0.3
Summary: Adsorption Based on ASE
Author-email: LiuGaoyong <liugaoyong_88@163.com>
Requires-Python: >=3.10
License-File: LICENSE
Requires-Dist: GraphAtoms>=0.0.2
Requires-Dist: pygfn0>=0.0.2
Requires-Dist: pygfnff>=0.0.2
Requires-Dist: scikit-optimize>=0.10.2
Requires-Dist: typing-extensions
Dynamic: license-file
